textcheck/__init__.py
textcheck/lib/__init__.py
textcheck/lib/spellcheck.py
textcheck/main.py
textcheck-0.2.2.dist-info/entry_points.txt
textcheck-0.2.2.dist-info/WHEEL
textcheck-0.2.2.dist-info/METADATA
textcheck-0.2.2.dist-info/RECORD
