Metadata-Version: 2.1
Name: textcheck
Version: 0.2.2
Summary: Check text files for issues.
Home-page: https://github.com/stribny/textcheck
License: MIT
Keywords: text,spellcheck
Author: Petr Stribny
Author-email: petr@stribny.name
Requires-Python: >=3.9,<4.0
Classifier: Development Status :: 3 - Alpha
Classifier: Environment :: Console
Classifier: License :: OSI Approved :: MIT License
Classifier: Operating System :: POSIX :: Linux
Classifier: Programming Language :: Python :: 3
Classifier: Programming Language :: Python :: 3.9
Classifier: Topic :: Text Processing
Requires-Dist: rich
Requires-Dist: spacy (==2.3.7)
Requires-Dist: spacy_hunspell (>=0.1.0,<0.2.0)
Requires-Dist: stackprinter
Requires-Dist: typer
Project-URL: Repository, https://github.com/stribny/textcheck
